voxta_gateway/__init__.py
voxta_gateway/client.py
voxta_gateway/event_emitter.py
voxta_gateway/gateway.py
voxta_gateway/main.py
voxta_gateway/sentence_buffer.py
voxta_gateway/state.py
voxta_gateway/voxta_bridge.py
voxta_gateway/websocket_manager.py
voxta_gateway-0.1.0.dist-info/licenses/LICENSE
voxta_gateway-0.1.0.dist-info/METADATA
voxta_gateway-0.1.0.dist-info/WHEEL
voxta_gateway-0.1.0.dist-info/entry_points.txt
voxta_gateway-0.1.0.dist-info/top_level.txt
voxta_gateway-0.1.0.dist-info/RECORD
