Metadata-Version: 2.4
Name: voxta-gateway
Version: 0.1.0
Summary: A state-mirroring gateway for the Voxta conversational AI platform, providing high-level semantic APIs for downstream applications.
Author: Dion Labs
License-Expression: MIT
Project-URL: Homepage, https://github.com/dion-labs/voxta-gateway
Classifier: Development Status :: 3 - Alpha
Classifier: Intended Audience :: Developers
Classifier: Programming Language :: Python :: 3
Classifier: Programming Language :: Python :: 3.10
Classifier: Programming Language :: Python :: 3.11
Classifier: Programming Language :: Python :: 3.12
Classifier: Operating System :: OS Independent
Classifier: Topic :: Scientific/Engineering :: Artificial Intelligence
Classifier: Topic :: Software Development :: Libraries :: Python Modules
Classifier: Framework :: FastAPI
Requires-Python: >=3.10
License-File: LICENSE
Requires-Dist: fastapi>=0.109.0
Requires-Dist: uvicorn[standard]>=0.27.0
Requires-Dist: voxta-client>=0.2.0
Requires-Dist: pydantic>=2.5.0
Requires-Dist: websockets>=12.0
Requires-Dist: httpx>=0.26.0
Provides-Extra: dev
Requires-Dist: ruff>=0.1.0; extra == "dev"
Requires-Dist: pre-commit>=3.5.0; extra == "dev"
Requires-Dist: pytest>=7.4.0; extra == "dev"
Requires-Dist: pytest-asyncio>=0.21.0; extra == "dev"
Requires-Dist: pytest-cov>=4.1.0; extra == "dev"
Requires-Dist: coverage-badge>=1.1.0; extra == "dev"
Provides-Extra: docs
Requires-Dist: mkdocs-material>=9.5.0; extra == "docs"
Requires-Dist: mkdocstrings[python]>=0.24.0; extra == "docs"
Requires-Dist: pymdown-extensions>=10.0; extra == "docs"
Dynamic: license-file
